compassheadinglib/__init__.py
compassheadinglib/__version__.py
compassheadinglib/common.py
compassheadinglib/compass_data.json
compassheadinglib/__pycache__/__init__.cpython-313.pyc
compassheadinglib/__pycache__/common.cpython-313.pyc
compassheadinglib-2025.8.19.dist-info/licenses/LICENSE
compassheadinglib-2025.8.19.dist-info/METADATA
compassheadinglib-2025.8.19.dist-info/WHEEL
compassheadinglib-2025.8.19.dist-info/top_level.txt
compassheadinglib-2025.8.19.dist-info/RECORD
