Metadata-Version: 2.4
Name: compassheadinglib
Version: 2025.8.19
Summary: A small, pure-python library for converting 360-decimal-degree headings (like 90.756) into human-friendly names and concepts (like 'Northeast' or 'Southeast by East') in multiple languages.
Author-email: Peter E Lenz <pelenz@pelenz.com>
License: MIT
Project-URL: Homepage, https://github.com/Peter-E-Lenz/compassheadinglib
Project-URL: Repository, https://github.com/Peter-E-Lenz/compassheadinglib
Project-URL: Issues, https://github.com/Peter-E-Lenz/compassheadinglib/issues
Keywords: compass,heading,navigation,gis,geography
Classifier: Development Status :: 2 - Pre-Alpha
Classifier: Programming Language :: Python :: 3
Classifier: License :: OSI Approved :: MIT License
Classifier: Operating System :: OS Independent
Classifier: Topic :: Scientific/Engineering :: GIS
Classifier: Intended Audience :: Developers
Classifier: Intended Audience :: Science/Research
Requires-Python: >=3.6.0
License-File: LICENSE
Provides-Extra: dev
Requires-Dist: pytest>=6.0; extra == "dev"
Requires-Dist: pytest-cov; extra == "dev"
Requires-Dist: build; extra == "dev"
Requires-Dist: twine; extra == "dev"
Provides-Extra: test
Requires-Dist: pytest>=6.0; extra == "test"
Requires-Dist: pytest-cov; extra == "test"
Dynamic: license-file
